MANIFEST.in
README.rst
setup.py
ragstoriches/__init__.py
ragstoriches/apps.py
ragstoriches/scraper.py
ragstoriches.egg-info/PKG-INFO
ragstoriches.egg-info/SOURCES.txt
ragstoriches.egg-info/dependency_links.txt
ragstoriches.egg-info/entry_points.txt
ragstoriches.egg-info/requires.txt
ragstoriches.egg-info/top_level.txt