Metadata-Version: 1.0
Name: ragstoriches
Version: 0.2
Summary: Develop highly-concurrent web scrapers, easily.
Home-page: http://github.com/mbr/ragstoriches
Author: Marc Brinkmann
Author-email: git@marcbrinkmann.de
License: MIT
Platform: UNKNOWN
